cursor_multi/__init__.py
cursor_multi/__main__.py
cursor_multi/_version.py
cursor_multi/cli.py
cursor_multi/cli_helpers.py
cursor_multi/errors.py
cursor_multi/git_helpers.py
cursor_multi/git_merge_branch.py
cursor_multi/git_run.py
cursor_multi/git_set_branch.py
cursor_multi/ignore_files.py
cursor_multi/init.py
cursor_multi/init_readme.py
cursor_multi/logging.py
cursor_multi/paths.py
cursor_multi/repos.py
cursor_multi/rules.py
cursor_multi/settings.py
cursor_multi/sync.py
cursor_multi/sync_cursor_rules.py
cursor_multi/sync_vscode.py
cursor_multi/sync_vscode_extensions.py
cursor_multi/sync_vscode_helpers.py
cursor_multi/sync_vscode_launch.py
cursor_multi/sync_vscode_settings.py
cursor_multi/sync_vscode_tasks.py
cursor_multi/utils.py
cursor_multi-1.1.10.dist-info/METADATA
cursor_multi-1.1.10.dist-info/WHEEL
cursor_multi-1.1.10.dist-info/entry_points.txt
cursor_multi-1.1.10.dist-info/licenses/LICENSE
cursor_multi-1.1.10.dist-info/RECORD
